Workbook

Sheet Resumen
A1: Resumen de costos – App de administración Majo
A2: Elaboración por fase, mantenimiento y costo del primer año. Montos en USD.
A4: Concepto | B4: Horas | C4: Costo (USD)
A5: Fase 0 – Inicio | B5: =Elaboración!E35/Elaboración!E40*Elaboración!E45 | C5: =Elaboración!F35/Elaboración!F40*Elaboración!F45
A6: Fase 1 – Recordatorios, Favorita, Pagos, Proveedores | B6: =Elaboración!E36/Elaboración!E40*Elaboración!E45 | C6: =Elaboración!F36/Elaboración!F40*Elaboración!F45
A7: Fase 2 – Cobros y Producción | B7: =Elaboración!E37/Elaboración!E40*Elaboración!E45 | C7: =Elaboración!F37/Elaboración!F40*Elaboración!F45
A8: Fase 3 – Reportes y llenado automático | B8: =Elaboración!E38/Elaboración!E40*Elaboración!E45 | C8: =Elaboración!F38/Elaboración!F40*Elaboración!F45
A9: Cierre – Capacitación y manual | B9: =Elaboración!E39/Elaboración!E40*Elaboración!E45 | C9: =Elaboración!F39/Elaboración!F40*Elaboración!F45
A10: Total elaboración (incluye QA, gestión y contingencia) | B10: =SUM(B5:B9) | C10: =SUM(C5:C9)
A12: Mantenimiento | B12: Económico (USD) | C12: Recomendado (USD)
A13: Mensual | B13: =Mantenimiento!C12 | C13: =Mantenimiento!E12
A14: Anual | B14: =Mantenimiento!C13 | C14: =Mantenimiento!E13
A15: Costo primer año (elaboración + 12 meses) | B15: =C10+B14 | C15: =C10+C14
A16: Costo solo fase 1 + 12 meses (arranque mínimo) | B16: =C5+C6+C9+B14 | C16: =C5+C6+C9+C14
A18: Referencia RNF-07: el facturador actual cuesta 110 USD al año. Tarifa y supuestos editables en la hoja Supuestos.

Sheet Supuestos
A1: Supuestos – App de administración Majo
A2: Celdas en azul con fondo amarillo: editables. Todo lo demás se recalcula. Montos en USD (RNF-05).
A4: Supuesto | B4: Valor | C4: Nota
A5: Tarifa por hora del desarrollador (USD) | B5: 20 | C5: Promedio freelance en Ecuador para desarrollo web full-stack. Ajustar a la tarifa real.
A6: Pruebas y control de calidad (% sobre horas de desarrollo) | B6: 0.15 | C6: Pruebas automáticas (vitest) y pruebas manuales en celular.
A7: Gestión del proyecto (% sobre horas de desarrollo) | B7: 0.1 | C7: Reuniones con Majo, seguimiento y ajustes de alcance.
A8: Contingencia (% sobre subtotal) | B8: 0.1 | C8: Cubre las 11 preguntas abiertas del documento de requerimientos.
A9: Mensajes de WhatsApp al mes | B9: 900 | C9: ≈10 obligaciones al día × 3 avisos (2 días, 1 día, 2 h) + repeticiones y respaldo (RF-02 a RF-04).
A10: Costo por mensaje de WhatsApp (USD) | B10: 0.01 | C10: Plantilla de utilidad de WhatsApp Cloud API (Meta), región resto de Latinoamérica. Verificar tarifa vigente en developers.facebook.com.
A11: Horas de soporte al mes – escenario económico | B11: 2 | C11: Correcciones menores y dudas de uso.
A12: Horas de soporte al mes – escenario recomendado | B12: 4 | C12: Correcciones, actualizaciones de seguridad y pequeños ajustes.
A13: Dominio .com al año (USD) | B13: 12 | C13: Opcional; .ec cuesta ≈35–40 USD/año.

Sheet Elaboración
A1: Costo de elaboración (pago único)
A2: Horas estimadas por módulo según Requerimientos_app_Majo.docx. Horas en azul: editables.
A4: Fase | B4: Módulo | C4: Actividad | D4: Requerimientos | E4: Horas | F4: Costo (USD)
A5: 0 | B5: Inicio | C5: Levantamiento de requerimientos (3 audios, transcripción, documento) | D5: — | E5: 12 | F5: =E5*Supuestos!$B$5
A6: 0 | B6: Inicio | C6: Diseño de pantallas y base de datos (Supabase, roles, seguridad RLS) | D6: RNF-01, RNF-02, RNF-04 | E6: 20 | F6: =E6*Supuestos!$B$5
A7: 0 | B7: Inicio | C7: Configuración del proyecto, inicio de sesión y despliegue | D7: RNF-04, RNF-05 | E7: 16 | F7: =E7*Supuestos!$B$5
A8: 1 | B8: M1 Recordatorios | C8: Registro de obligaciones con frecuencia y responsable | D8: RF-01 | E8: 14 | F8: =E8*Supuestos!$B$5
A9: 1 | B9: M1 Recordatorios | C9: Motor de avisos programados (cron) con anticipación configurable | D9: RF-02, RF-03, RNF-08 | E9: 14 | F9: =E9*Supuestos!$B$5
A10: 1 | B10: M1 Recordatorios | C10: Integración WhatsApp Cloud API y correo alternativo | D10: RF-02, RNF-03 | E10: 12 | F10: =E10*Supuestos!$B$5
A11: 1 | B11: M1 Recordatorios | C11: Aviso a responsable de respaldo y marcar "hecho" | D11: RF-04, RF-05 | E11: 10 | F11: =E11*Supuestos!$B$5
A12: 1 | B12: M1 Recordatorios | C12: Pantalla "Hoy y esta semana" y obligaciones precargadas | D12: RF-06, RF-07 | E12: 10 | F12: =E12*Supuestos!$B$5
A13: 1 | B13: M1 Recordatorios | C13: Panel de administración con gráficas (avisos y cumplimiento) | D13: RF-05, RNF-04 | E13: 20 | F13: =E13*Supuestos!$B$5
A14: 1 | B14: M2 Favorita | C14: Enlace semanal de oferta y avisos hasta el miércoles 19:00 | D14: RF-08 | E14: 8 | F14: =E14*Supuestos!$B$5
A15: 1 | B15: M2 Favorita | C15: Catálogo de productos ofertados y oferta lista para copiar | D15: RF-09, RF-10 | E15: 14 | F15: =E15*Supuestos!$B$5
A16: 1 | B16: M2 Favorita | C16: Control de capacidad de buseta (100 javas) | D16: RF-11 | E16: 4 | F16: =E16*Supuestos!$B$5
... A33: Cierre | B33: Entrega | C33: Manual de uso sencillo | D33: RNF-02 | E33: 6 | F33: =E33*Supuestos!$B$5
C35: Subtotal fase 0 – Inicio | E35: =SUMIFS($E$5:$E$33,$A$5:$A$33,"0") | F35: =E35*Supuestos!$B$5
C36: Subtotal fase 1 – M1 a M4 | E36: =SUMIFS($E$5:$E$33,$A$5:$A$33,"1") | F36: =E36*Supuestos!$B$5
C37: Subtotal fase 2 – M5 y M6 | E37: =SUMIFS($E$5:$E$33,$A$5:$A$33,"2") | F37: =E37*Supuestos!$B$5
C38: Subtotal fase 3 – M7 y RF-14 | E38: =SUMIFS($E$5:$E$33,$A$5:$A$33,"3") | F38: =E38*Supuestos!$B$5
C39: Subtotal cierre – capacitación y manual | E39: =SUMIFS($E$5:$E$33,$A$5:$A$33,"Cierre") | F39: =E39*Supuestos!$B$5
C40: Horas de desarrollo | E40: =SUM(E35:E39) | F40: =E40*Supuestos!$B$5
C41: Pruebas y control de calidad | E41: =E40*Supuestos!$B$6 | F41: =E41*Supuestos!$B$5
C42: Gestión del proyecto | E42: =E40*Supuestos!$B$7 | F42: =E42*Supuestos!$B$5
C43: Subtotal | E43: =E40+E41+E42 | F43: =F40+F41+F42
C44: Contingencia | E44: =E43*Supuestos!$B$8 | F44: =F43*Supuestos!$B$8
C45: TOTAL ELABORACIÓN | E45: =E43+E44 | F45: =F43+F44
A47: QA, gestión y contingencia se reparten entre fases en proporción a sus horas (ver hoja Resumen).

Sheet Mantenimiento
A1: Costo de mantenimiento (recurrente)
A2: Dos escenarios. RNF-07 pide costo bajo; RNF-06 pide respaldo diario. Montos en USD.
A4: Concepto | B4: Escenario económico | C4: Mensual econ. (USD) | D4: Escenario recomendado | E4: Mensual recom. (USD)
A5: Hosting web (Vercel) | B5: Plan Hobby: gratis, pero solo uso no comercial | C5: 0 | D5: Plan Pro: uso comercial, cron cada minuto | E5: 20
A6: Base de datos e inicio de sesión (Supabase) | B6: Plan Free: 500 MB, sin respaldos automáticos | C6: 0 | D6: Plan Pro: 8 GB y respaldo diario automático (RNF-06) | E6: 25
A7: Respaldo diario de datos | B7: Script en GitHub Actions (gratis) | C7: 0 | D7: Incluido en Supabase Pro | E7: 0
A8: Programador de avisos (cron) | B8: cron-job.org cada 5 min (gratis) | C8: 0 | D8: Incluido en Vercel Pro | E8: 0
A9: Mensajes de WhatsApp (Meta Cloud API) | B9: Según volumen de la hoja Supuestos | C9: =Supuestos!$B$9*Supuestos!$B$10 | D9: Según volumen de la hoja Supuestos | E9: =Supuestos!$B$9*Supuestos!$B$10
A10: Dominio .com | B10: Prorrateo mensual | C10: =Supuestos!$B$13/12 | D10: Prorrateo mensual | E10: =Supuestos!$B$13/12
A11: Soporte y correcciones | B11: Horas al mes × tarifa | C11: =Supuestos!$B$11*Supuestos!$B$5 | D11: Horas al mes × tarifa | E11: =Supuestos!$B$12*Supuestos!$B$5
A12: Total mensual | C12: =SUM(C5:C11) | E12: =SUM(E5:E11)
A13: Total anual | C13: =C12*12 | E13: =E12*12
A15: • Costos únicos de arranque: chip para número de WhatsApp Business ≈5 USD; verificación de la cuenta de Meta: gratis.
A16: • Vercel Hobby prohíbe uso comercial: el escenario económico sirve para pruebas o arranque; para producción conviene Pro.
A17: • Supabase Free pausa el proyecto tras 7 días sin actividad; el cron de avisos lo mantiene activo.
A18: • Precios de Vercel, Supabase y Meta consultados al conocimiento de 2026; confirmar en sus páginas antes de contratar.
